[
    {
        "%vlocity_namespace%__DomainObjectAPIName__c": "json",
        "%vlocity_namespace%__DomainObjectCreationOrder__c": 0,
        "%vlocity_namespace%__DomainObjectFieldAPIName__c": "Contact",
        "%vlocity_namespace%__FilterGroup__c": 0,
        "%vlocity_namespace%__FilterOperator__c": "LIKE",
        "%vlocity_namespace%__FilterValue__c": "DRTPAContactName",
        "%vlocity_namespace%__InterfaceFieldAPIName__c": "Name",
        "%vlocity_namespace%__InterfaceObjectLookupOrder__c": 1,
        "%vlocity_namespace%__InterfaceObjectName__c": "Contact",
        "%vlocity_namespace%__IsDisabled__c": false,
        "%vlocity_namespace%__IsRequiredForUpsert__c": false,
        "%vlocity_namespace%__MapId__c": "IMP_FundingContactV2Customa26W0000001r1kaIAAItem3",
        "%vlocity_namespace%__UpsertKey__c": false,
        "Name": "IMP_FundingContactV2",
        "VlocityDataPackType": "SObject",
        "VlocityRecordSObjectType": "%vlocity_namespace%__DRMapItem__c"
    },
    {
        "%vlocity_namespace%__DomainObjectAPIName__c": "json",
        "%vlocity_namespace%__DomainObjectCreationOrder__c": 0,
        "%vlocity_namespace%__DomainObjectFieldAPIName__c": "Contact",
        "%vlocity_namespace%__FilterGroup__c": 0,
        "%vlocity_namespace%__FilterOperator__c": "LIMIT",
        "%vlocity_namespace%__FilterValue__c": "20",
        "%vlocity_namespace%__InterfaceObjectLookupOrder__c": 1,
        "%vlocity_namespace%__InterfaceObjectName__c": "Contact",
        "%vlocity_namespace%__IsDisabled__c": false,
        "%vlocity_namespace%__IsRequiredForUpsert__c": false,
        "%vlocity_namespace%__MapId__c": "IMP_FundingContactV2Custom3656",
        "%vlocity_namespace%__UpsertKey__c": false,
        "Name": "IMP_FundingContactV2",
        "VlocityDataPackType": "SObject",
        "VlocityRecordSObjectType": "%vlocity_namespace%__DRMapItem__c"
    },
    {
        "%vlocity_namespace%__DomainObjectAPIName__c": "json",
        "%vlocity_namespace%__DomainObjectCreationOrder__c": 1,
        "%vlocity_namespace%__DomainObjectFieldAPIName__c": "TPAContactId",
        "%vlocity_namespace%__InterfaceFieldAPIName__c": "Contact:Id",
        "%vlocity_namespace%__IsDisabled__c": false,
        "%vlocity_namespace%__IsRequiredForUpsert__c": false,
        "%vlocity_namespace%__MapId__c": "IMP_FundingContactV2Customa26W0000001r1kaIAAItem4",
        "%vlocity_namespace%__UpsertKey__c": false,
        "Name": "IMP_FundingContactV2",
        "VlocityDataPackType": "SObject",
        "VlocityRecordSObjectType": "%vlocity_namespace%__DRMapItem__c"
    },
    {
        "%vlocity_namespace%__DomainObjectAPIName__c": "json",
        "%vlocity_namespace%__DomainObjectCreationOrder__c": 1,
        "%vlocity_namespace%__DomainObjectFieldAPIName__c": "TPADisplayName",
        "%vlocity_namespace%__InterfaceFieldAPIName__c": "Contact:TPA_Display_Name__c",
        "%vlocity_namespace%__IsDisabled__c": false,
        "%vlocity_namespace%__IsRequiredForUpsert__c": false,
        "%vlocity_namespace%__MapId__c": "IMP_FundingContactV2Custom2580",
        "%vlocity_namespace%__UpsertKey__c": false,
        "Name": "IMP_FundingContactV2",
        "VlocityDataPackType": "SObject",
        "VlocityRecordSObjectType": "%vlocity_namespace%__DRMapItem__c"
    },
    {
        "%vlocity_namespace%__DomainObjectAPIName__c": "json",
        "%vlocity_namespace%__DomainObjectCreationOrder__c": 1,
        "%vlocity_namespace%__DomainObjectFieldAPIName__c": "TPAMailingCity",
        "%vlocity_namespace%__InterfaceFieldAPIName__c": "Contact:MailingCity",
        "%vlocity_namespace%__IsDisabled__c": false,
        "%vlocity_namespace%__IsRequiredForUpsert__c": false,
        "%vlocity_namespace%__MapId__c": "IMP_FundingContactV2Customa26W0000001r1kaIAAItem5",
        "%vlocity_namespace%__UpsertKey__c": false,
        "Name": "IMP_FundingContactV2",
        "VlocityDataPackType": "SObject",
        "VlocityRecordSObjectType": "%vlocity_namespace%__DRMapItem__c"
    },
    {
        "%vlocity_namespace%__DomainObjectAPIName__c": "json",
        "%vlocity_namespace%__DomainObjectCreationOrder__c": 1,
        "%vlocity_namespace%__DomainObjectFieldAPIName__c": "TPAMailingState",
        "%vlocity_namespace%__InterfaceFieldAPIName__c": "Contact:MailingState",
        "%vlocity_namespace%__IsDisabled__c": false,
        "%vlocity_namespace%__IsRequiredForUpsert__c": false,
        "%vlocity_namespace%__MapId__c": "IMP_FundingContactV2Customa26W0000001r1kaIAAItem7",
        "%vlocity_namespace%__UpsertKey__c": false,
        "Name": "IMP_FundingContactV2",
        "VlocityDataPackType": "SObject",
        "VlocityRecordSObjectType": "%vlocity_namespace%__DRMapItem__c"
    },
    {
        "%vlocity_namespace%__DomainObjectAPIName__c": "json",
        "%vlocity_namespace%__DomainObjectCreationOrder__c": 1,
        "%vlocity_namespace%__DomainObjectFieldAPIName__c": "TPAMailingStreet",
        "%vlocity_namespace%__InterfaceFieldAPIName__c": "Contact:MailingStreet",
        "%vlocity_namespace%__IsDisabled__c": false,
        "%vlocity_namespace%__IsRequiredForUpsert__c": false,
        "%vlocity_namespace%__MapId__c": "IMP_FundingContactV2Customa26W0000001r1kaIAAItem8",
        "%vlocity_namespace%__UpsertKey__c": false,
        "Name": "IMP_FundingContactV2",
        "VlocityDataPackType": "SObject",
        "VlocityRecordSObjectType": "%vlocity_namespace%__DRMapItem__c"
    },
    {
        "%vlocity_namespace%__DomainObjectAPIName__c": "json",
        "%vlocity_namespace%__DomainObjectCreationOrder__c": 1,
        "%vlocity_namespace%__DomainObjectFieldAPIName__c": "TPAMailingZipCode",
        "%vlocity_namespace%__InterfaceFieldAPIName__c": "Contact:MailingPostalCode",
        "%vlocity_namespace%__IsDisabled__c": false,
        "%vlocity_namespace%__IsRequiredForUpsert__c": false,
        "%vlocity_namespace%__MapId__c": "IMP_FundingContactV2Customa26W0000001r1kaIAAItem6",
        "%vlocity_namespace%__UpsertKey__c": false,
        "Name": "IMP_FundingContactV2",
        "VlocityDataPackType": "SObject",
        "VlocityRecordSObjectType": "%vlocity_namespace%__DRMapItem__c"
    },
    {
        "%vlocity_namespace%__DomainObjectAPIName__c": "json",
        "%vlocity_namespace%__DomainObjectCreationOrder__c": 1,
        "%vlocity_namespace%__DomainObjectFieldAPIName__c": "TPAName",
        "%vlocity_namespace%__InterfaceFieldAPIName__c": "Contact:Name",
        "%vlocity_namespace%__IsDisabled__c": false,
        "%vlocity_namespace%__IsRequiredForUpsert__c": false,
        "%vlocity_namespace%__MapId__c": "IMP_FundingContactV2Customa26W0000001r1kaIAAItem9",
        "%vlocity_namespace%__UpsertKey__c": false,
        "Name": "IMP_FundingContactV2",
        "VlocityDataPackType": "SObject",
        "VlocityRecordSObjectType": "%vlocity_namespace%__DRMapItem__c"
    },
    {
        "%vlocity_namespace%__DomainObjectAPIName__c": "json",
        "%vlocity_namespace%__DomainObjectCreationOrder__c": 1,
        "%vlocity_namespace%__DomainObjectFieldAPIName__c": "TPAPhone",
        "%vlocity_namespace%__InterfaceFieldAPIName__c": "Contact:Phone",
        "%vlocity_namespace%__IsDisabled__c": false,
        "%vlocity_namespace%__IsRequiredForUpsert__c": false,
        "%vlocity_namespace%__MapId__c": "IMP_FundingContactV2Customa26W0000001r1kaIAAItem10",
        "%vlocity_namespace%__UpsertKey__c": false,
        "Name": "IMP_FundingContactV2",
        "VlocityDataPackType": "SObject",
        "VlocityRecordSObjectType": "%vlocity_namespace%__DRMapItem__c"
    }
]