[
    {
        "%vlocity_namespace%__DomainObjectAPIName__c": "Eligibility__c",
        "%vlocity_namespace%__DomainObjectCreationOrder__c": 1,
        "%vlocity_namespace%__DomainObjectFieldAPIName__c": "COBRA_Administration_Services_Provided__c",
        "%vlocity_namespace%__InterfaceFieldAPIName__c": "EligibilityInformation:COBRAAdministrationServices",
        "%vlocity_namespace%__IsDisabled__c": false,
        "%vlocity_namespace%__IsRequiredForUpsert__c": false,
        "%vlocity_namespace%__MapId__c": "EligibilityUpdatesLoadGroupCustom2285",
        "%vlocity_namespace%__UpsertKey__c": false,
        "Name": "EligibilityUpdatesLoadGroup",
        "VlocityDataPackType": "SObject",
        "VlocityRecordSObjectType": "%vlocity_namespace%__DRMapItem__c"
    },
    {
        "%vlocity_namespace%__DomainObjectAPIName__c": "Eligibility__c",
        "%vlocity_namespace%__DomainObjectCreationOrder__c": 1,
        "%vlocity_namespace%__DomainObjectFieldAPIName__c": "Delete_Dependent_Code__c",
        "%vlocity_namespace%__InterfaceFieldAPIName__c": "EligibilityInformation:DeleteDependentCode",
        "%vlocity_namespace%__IsDisabled__c": false,
        "%vlocity_namespace%__IsRequiredForUpsert__c": false,
        "%vlocity_namespace%__MapId__c": "EligibilityUpdatesLoadGroupCustom7165",
        "%vlocity_namespace%__UpsertKey__c": false,
        "Name": "EligibilityUpdatesLoadGroup",
        "VlocityDataPackType": "SObject",
        "VlocityRecordSObjectType": "%vlocity_namespace%__DRMapItem__c"
    },
    {
        "%vlocity_namespace%__DomainObjectAPIName__c": "Eligibility__c",
        "%vlocity_namespace%__DomainObjectCreationOrder__c": 1,
        "%vlocity_namespace%__DomainObjectFieldAPIName__c": "Domestic_Partner_Indicator__c",
        "%vlocity_namespace%__InterfaceFieldAPIName__c": "EligibilityInformation:DomesticPartnerIndicator",
        "%vlocity_namespace%__IsDisabled__c": false,
        "%vlocity_namespace%__IsRequiredForUpsert__c": false,
        "%vlocity_namespace%__MapId__c": "EligibilityUpdatesLoadGroupCustom2488",
        "%vlocity_namespace%__UpsertKey__c": false,
        "Name": "EligibilityUpdatesLoadGroup",
        "VlocityDataPackType": "SObject",
        "VlocityRecordSObjectType": "%vlocity_namespace%__DRMapItem__c"
    },
    {
        "%vlocity_namespace%__DomainObjectAPIName__c": "Eligibility__c",
        "%vlocity_namespace%__DomainObjectCreationOrder__c": 1,
        "%vlocity_namespace%__DomainObjectFieldAPIName__c": "Employee_Excluded_Code__c",
        "%vlocity_namespace%__InterfaceFieldAPIName__c": "EligibilityInformation:EmployeeExcludedCode",
        "%vlocity_namespace%__IsDisabled__c": false,
        "%vlocity_namespace%__IsRequiredForUpsert__c": false,
        "%vlocity_namespace%__MapId__c": "EligibilityUpdatesLoadGroupCustom3624",
        "%vlocity_namespace%__UpsertKey__c": false,
        "Name": "EligibilityUpdatesLoadGroup",
        "VlocityDataPackType": "SObject",
        "VlocityRecordSObjectType": "%vlocity_namespace%__DRMapItem__c"
    },
    {
        "%vlocity_namespace%__DomainObjectAPIName__c": "Eligibility__c",
        "%vlocity_namespace%__DomainObjectCreationOrder__c": 1,
        "%vlocity_namespace%__DomainObjectFieldAPIName__c": "Id",
        "%vlocity_namespace%__InterfaceFieldAPIName__c": "EligbleId",
        "%vlocity_namespace%__IsDisabled__c": false,
        "%vlocity_namespace%__IsRequiredForUpsert__c": false,
        "%vlocity_namespace%__MapId__c": "EligibilityUpdatesLoadGroupCustom7932",
        "%vlocity_namespace%__UpsertKey__c": true,
        "Name": "EligibilityUpdatesLoadGroup",
        "VlocityDataPackType": "SObject",
        "VlocityRecordSObjectType": "%vlocity_namespace%__DRMapItem__c"
    },
    {
        "%vlocity_namespace%__ConfigurationValue__c": "FAKEMAPPING",
        "%vlocity_namespace%__DomainObjectAPIName__c": "Eligibility__c",
        "%vlocity_namespace%__DomainObjectCreationOrder__c": 1,
        "%vlocity_namespace%__DomainObjectFieldAPIName__c": "Id",
        "%vlocity_namespace%__FilterOperator__c": "=",
        "%vlocity_namespace%__IsDisabled__c": true,
        "%vlocity_namespace%__IsRequiredForUpsert__c": false,
        "%vlocity_namespace%__MapId__c": "EligibilityUpdatesLoadGroupCustom5647",
        "%vlocity_namespace%__UpsertKey__c": false,
        "Name": "EligibilityUpdatesLoadGroup",
        "VlocityDataPackType": "SObject",
        "VlocityRecordSObjectType": "%vlocity_namespace%__DRMapItem__c"
    },
    {
        "%vlocity_namespace%__DomainObjectAPIName__c": "Eligibility__c",
        "%vlocity_namespace%__DomainObjectCreationOrder__c": 1,
        "%vlocity_namespace%__DomainObjectFieldAPIName__c": "Over_65_Code__c",
        "%vlocity_namespace%__InterfaceFieldAPIName__c": "EligibilityInformation:Over65Code",
        "%vlocity_namespace%__IsDisabled__c": false,
        "%vlocity_namespace%__IsRequiredForUpsert__c": false,
        "%vlocity_namespace%__MapId__c": "EligibilityUpdatesLoadGroupCustom8775",
        "%vlocity_namespace%__UpsertKey__c": false,
        "Name": "EligibilityUpdatesLoadGroup",
        "VlocityDataPackType": "SObject",
        "VlocityRecordSObjectType": "%vlocity_namespace%__DRMapItem__c"
    },
    {
        "%vlocity_namespace%__DomainObjectAPIName__c": "Eligibility__c",
        "%vlocity_namespace%__DomainObjectCreationOrder__c": 1,
        "%vlocity_namespace%__DomainObjectFieldAPIName__c": "Overage_dep_term_Itrs_be_mailed_to_sub__c",
        "%vlocity_namespace%__InterfaceFieldAPIName__c": "EligibilityInformation:OverageDepTermLettersMailedtoSub",
        "%vlocity_namespace%__IsDisabled__c": false,
        "%vlocity_namespace%__IsRequiredForUpsert__c": false,
        "%vlocity_namespace%__MapId__c": "EligibilityUpdatesLoadGroupCustom6848",
        "%vlocity_namespace%__UpsertKey__c": false,
        "Name": "EligibilityUpdatesLoadGroup",
        "VlocityDataPackType": "SObject",
        "VlocityRecordSObjectType": "%vlocity_namespace%__DRMapItem__c"
    },
    {
        "%vlocity_namespace%__DomainObjectAPIName__c": "Eligibility__c",
        "%vlocity_namespace%__DomainObjectCreationOrder__c": 1,
        "%vlocity_namespace%__DomainObjectFieldAPIName__c": "Prem_Paid_for_Each_Sub_Dep_per_Month__c",
        "%vlocity_namespace%__InterfaceFieldAPIName__c": "EligibilityInformation:PremPaidForEachSubDepPerMonth",
        "%vlocity_namespace%__IsDisabled__c": false,
        "%vlocity_namespace%__IsRequiredForUpsert__c": false,
        "%vlocity_namespace%__MapId__c": "EligibilityUpdatesLoadGroupCustom3297",
        "%vlocity_namespace%__UpsertKey__c": false,
        "Name": "EligibilityUpdatesLoadGroup",
        "VlocityDataPackType": "SObject",
        "VlocityRecordSObjectType": "%vlocity_namespace%__DRMapItem__c"
    },
    {
        "%vlocity_namespace%__DomainObjectAPIName__c": "Eligibility__c",
        "%vlocity_namespace%__DomainObjectCreationOrder__c": 1,
        "%vlocity_namespace%__DomainObjectFieldAPIName__c": "Prem_Paid_for_Each_Sub_per_Month__c",
        "%vlocity_namespace%__InterfaceFieldAPIName__c": "EligibilityInformation:PremPaidForEachSubPerMonth",
        "%vlocity_namespace%__IsDisabled__c": false,
        "%vlocity_namespace%__IsRequiredForUpsert__c": false,
        "%vlocity_namespace%__MapId__c": "EligibilityUpdatesLoadGroupCustom6581",
        "%vlocity_namespace%__UpsertKey__c": false,
        "Name": "EligibilityUpdatesLoadGroup",
        "VlocityDataPackType": "SObject",
        "VlocityRecordSObjectType": "%vlocity_namespace%__DRMapItem__c"
    },
    {
        "%vlocity_namespace%__DomainObjectAPIName__c": "Eligibility__c",
        "%vlocity_namespace%__DomainObjectCreationOrder__c": 1,
        "%vlocity_namespace%__DomainObjectFieldAPIName__c": "Women_s_Contraceptive_Exemption_Ind__c",
        "%vlocity_namespace%__InterfaceFieldAPIName__c": "EligibilityInformation:WomenContraceptiveInd",
        "%vlocity_namespace%__IsDisabled__c": false,
        "%vlocity_namespace%__IsRequiredForUpsert__c": false,
        "%vlocity_namespace%__MapId__c": "EligibilityUpdatesLoadGroupCustom8529",
        "%vlocity_namespace%__UpsertKey__c": false,
        "Name": "EligibilityUpdatesLoadGroup",
        "VlocityDataPackType": "SObject",
        "VlocityRecordSObjectType": "%vlocity_namespace%__DRMapItem__c"
    },
    {
        "%vlocity_namespace%__DomainObjectAPIName__c": "Account",
        "%vlocity_namespace%__DomainObjectCreationOrder__c": 2,
        "%vlocity_namespace%__DomainObjectFieldAPIName__c": "Id",
        "%vlocity_namespace%__InterfaceFieldAPIName__c": "AccountUpdateId",
        "%vlocity_namespace%__IsDisabled__c": false,
        "%vlocity_namespace%__IsRequiredForUpsert__c": false,
        "%vlocity_namespace%__MapId__c": "EligibilityUpdatesLoadGroupCustom8717",
        "%vlocity_namespace%__UpsertKey__c": true,
        "Name": "EligibilityUpdatesLoadGroup",
        "VlocityDataPackType": "SObject",
        "VlocityRecordSObjectType": "%vlocity_namespace%__DRMapItem__c"
    },
    {
        "%vlocity_namespace%__ConfigurationValue__c": "FAKEMAPPING",
        "%vlocity_namespace%__DomainObjectAPIName__c": "Account",
        "%vlocity_namespace%__DomainObjectCreationOrder__c": 2,
        "%vlocity_namespace%__DomainObjectFieldAPIName__c": "Id",
        "%vlocity_namespace%__FilterOperator__c": "=",
        "%vlocity_namespace%__IsDisabled__c": true,
        "%vlocity_namespace%__IsRequiredForUpsert__c": false,
        "%vlocity_namespace%__MapId__c": "EligibilityUpdatesLoadGroupCustom9398",
        "%vlocity_namespace%__UpsertKey__c": false,
        "Name": "EligibilityUpdatesLoadGroup",
        "VlocityDataPackType": "SObject",
        "VlocityRecordSObjectType": "%vlocity_namespace%__DRMapItem__c"
    },
    {
        "%vlocity_namespace%__DomainObjectAPIName__c": "Account",
        "%vlocity_namespace%__DomainObjectCreationOrder__c": 2,
        "%vlocity_namespace%__DomainObjectFieldAPIName__c": "ProbationaryPeriod__c",
        "%vlocity_namespace%__InterfaceFieldAPIName__c": "EligibilityInformation:ProbationaryPeriod",
        "%vlocity_namespace%__IsDisabled__c": false,
        "%vlocity_namespace%__IsRequiredForUpsert__c": false,
        "%vlocity_namespace%__MapId__c": "EligibilityUpdatesLoadGroupCustom3142",
        "%vlocity_namespace%__UpsertKey__c": false,
        "Name": "EligibilityUpdatesLoadGroup",
        "VlocityDataPackType": "SObject",
        "VlocityRecordSObjectType": "%vlocity_namespace%__DRMapItem__c"
    }
]