[
    {
        "%vlocity_namespace%__DomainObjectAPIName__c": "Formula",
        "%vlocity_namespace%__DomainObjectCreationOrder__c": 0,
        "%vlocity_namespace%__DomainObjectFieldAPIName__c": "Formula",
        "%vlocity_namespace%__FormulaOrder__c": 1,
        "%vlocity_namespace%__FormulaResultPath__c": "KeepCompId",
        "%vlocity_namespace%__Formula__c": "IF(SelectServiceProvider:NOUFlag==true,'',SelectServiceProvider:CompetitorId)",
        "%vlocity_namespace%__InterfaceObjectName__c": "json",
        "%vlocity_namespace%__IsDisabled__c": false,
        "%vlocity_namespace%__IsRequiredForUpsert__c": false,
        "%vlocity_namespace%__LinkCreatedIndex__c": 0,
        "%vlocity_namespace%__MapId__c": "AP-OpptyAddQLIforVBundleCustom9181",
        "%vlocity_namespace%__UpsertKey__c": false,
        "Name": "AP-OpptyAddQLIforVBundle",
        "VlocityDataPackType": "SObject",
        "VlocityRecordSObjectType": "%vlocity_namespace%__DRMapItem__c"
    },
    {
        "%vlocity_namespace%__DomainObjectAPIName__c": "Formula",
        "%vlocity_namespace%__DomainObjectCreationOrder__c": 0,
        "%vlocity_namespace%__DomainObjectFieldAPIName__c": "Formula",
        "%vlocity_namespace%__FormulaOrder__c": 2,
        "%vlocity_namespace%__FormulaResultPath__c": "KeepCompStatus",
        "%vlocity_namespace%__Formula__c": "IF(SelectServiceProvider:NOUFlag==true,'',SelectServiceProvider:CompetitorStatusFormula)",
        "%vlocity_namespace%__InterfaceObjectName__c": "json",
        "%vlocity_namespace%__IsDisabled__c": false,
        "%vlocity_namespace%__IsRequiredForUpsert__c": false,
        "%vlocity_namespace%__LinkCreatedIndex__c": 0,
        "%vlocity_namespace%__MapId__c": "AP-OpptyAddQLIforVBundleCustom1682",
        "%vlocity_namespace%__UpsertKey__c": false,
        "Name": "AP-OpptyAddQLIforVBundle",
        "VlocityDataPackType": "SObject",
        "VlocityRecordSObjectType": "%vlocity_namespace%__DRMapItem__c"
    },
    {
        "%vlocity_namespace%__DomainObjectAPIName__c": "QuoteLineItem",
        "%vlocity_namespace%__DomainObjectCreationOrder__c": 1,
        "%vlocity_namespace%__DomainObjectFieldAPIName__c": "AnthemVendor__c",
        "%vlocity_namespace%__FormulaOrder__c": 0,
        "%vlocity_namespace%__InterfaceFieldAPIName__c": "QLD:QLD-Vendor",
        "%vlocity_namespace%__InterfaceObjectName__c": "json",
        "%vlocity_namespace%__IsDisabled__c": false,
        "%vlocity_namespace%__IsRequiredForUpsert__c": false,
        "%vlocity_namespace%__LinkCreatedIndex__c": 0,
        "%vlocity_namespace%__MapId__c": "AP-OpptyAddQLIforVBundleCustom8101",
        "%vlocity_namespace%__UpsertKey__c": false,
        "Name": "AP-OpptyAddQLIforVBundle",
        "VlocityDataPackType": "SObject",
        "VlocityRecordSObjectType": "%vlocity_namespace%__DRMapItem__c"
    },
    {
        "%vlocity_namespace%__DomainObjectAPIName__c": "QuoteLineItem",
        "%vlocity_namespace%__DomainObjectCreationOrder__c": 1,
        "%vlocity_namespace%__DomainObjectFieldAPIName__c": "Competitor2__c",
        "%vlocity_namespace%__FormulaOrder__c": 0,
        "%vlocity_namespace%__InterfaceFieldAPIName__c": "SelectServiceProvider:CompIdCalc2",
        "%vlocity_namespace%__InterfaceObjectName__c": "json",
        "%vlocity_namespace%__IsDisabled__c": false,
        "%vlocity_namespace%__IsRequiredForUpsert__c": false,
        "%vlocity_namespace%__LinkCreatedIndex__c": 0,
        "%vlocity_namespace%__MapId__c": "AP-OpptyAddQLIforVBundleCustom3938",
        "%vlocity_namespace%__UpsertKey__c": false,
        "Name": "AP-OpptyAddQLIforVBundle",
        "VlocityDataPackType": "SObject",
        "VlocityRecordSObjectType": "%vlocity_namespace%__DRMapItem__c"
    },
    {
        "%vlocity_namespace%__DomainObjectAPIName__c": "QuoteLineItem",
        "%vlocity_namespace%__DomainObjectCreationOrder__c": 1,
        "%vlocity_namespace%__DomainObjectFieldAPIName__c": "Competitor3__c",
        "%vlocity_namespace%__FormulaOrder__c": 0,
        "%vlocity_namespace%__InterfaceFieldAPIName__c": "SelectServiceProvider:CompIdCalc3",
        "%vlocity_namespace%__InterfaceObjectName__c": "json",
        "%vlocity_namespace%__IsDisabled__c": false,
        "%vlocity_namespace%__IsRequiredForUpsert__c": false,
        "%vlocity_namespace%__LinkCreatedIndex__c": 0,
        "%vlocity_namespace%__MapId__c": "AP-OpptyAddQLIforVBundleCustom9196",
        "%vlocity_namespace%__UpsertKey__c": false,
        "Name": "AP-OpptyAddQLIforVBundle",
        "VlocityDataPackType": "SObject",
        "VlocityRecordSObjectType": "%vlocity_namespace%__DRMapItem__c"
    },
    {
        "%vlocity_namespace%__DomainObjectAPIName__c": "QuoteLineItem",
        "%vlocity_namespace%__DomainObjectCreationOrder__c": 1,
        "%vlocity_namespace%__DomainObjectFieldAPIName__c": "CompetitorStatus2__c",
        "%vlocity_namespace%__FormulaOrder__c": 0,
        "%vlocity_namespace%__InterfaceFieldAPIName__c": "SelectServiceProvider:CompStatusCalc2",
        "%vlocity_namespace%__InterfaceObjectName__c": "json",
        "%vlocity_namespace%__IsDisabled__c": false,
        "%vlocity_namespace%__IsRequiredForUpsert__c": false,
        "%vlocity_namespace%__LinkCreatedIndex__c": 0,
        "%vlocity_namespace%__MapId__c": "AP-OpptyAddQLIforVBundleCustom3412",
        "%vlocity_namespace%__UpsertKey__c": false,
        "Name": "AP-OpptyAddQLIforVBundle",
        "VlocityDataPackType": "SObject",
        "VlocityRecordSObjectType": "%vlocity_namespace%__DRMapItem__c"
    },
    {
        "%vlocity_namespace%__DomainObjectAPIName__c": "QuoteLineItem",
        "%vlocity_namespace%__DomainObjectCreationOrder__c": 1,
        "%vlocity_namespace%__DomainObjectFieldAPIName__c": "CompetitorStatus3__c",
        "%vlocity_namespace%__FormulaOrder__c": 0,
        "%vlocity_namespace%__InterfaceFieldAPIName__c": "SelectServiceProvider:CompStatusCalc3",
        "%vlocity_namespace%__InterfaceObjectName__c": "json",
        "%vlocity_namespace%__IsDisabled__c": false,
        "%vlocity_namespace%__IsRequiredForUpsert__c": false,
        "%vlocity_namespace%__LinkCreatedIndex__c": 0,
        "%vlocity_namespace%__MapId__c": "AP-OpptyAddQLIforVBundleCustom513",
        "%vlocity_namespace%__UpsertKey__c": false,
        "Name": "AP-OpptyAddQLIforVBundle",
        "VlocityDataPackType": "SObject",
        "VlocityRecordSObjectType": "%vlocity_namespace%__DRMapItem__c"
    },
    {
        "%vlocity_namespace%__DomainObjectAPIName__c": "QuoteLineItem",
        "%vlocity_namespace%__DomainObjectCreationOrder__c": 1,
        "%vlocity_namespace%__DomainObjectFieldAPIName__c": "CompetitorStatus__c",
        "%vlocity_namespace%__FormulaOrder__c": 0,
        "%vlocity_namespace%__InterfaceFieldAPIName__c": "KeepCompStatus",
        "%vlocity_namespace%__InterfaceObjectName__c": "json",
        "%vlocity_namespace%__IsDisabled__c": false,
        "%vlocity_namespace%__IsRequiredForUpsert__c": false,
        "%vlocity_namespace%__LinkCreatedIndex__c": 0,
        "%vlocity_namespace%__MapId__c": "AP-OpptyAddQLIforVBundleCustom2726",
        "%vlocity_namespace%__UpsertKey__c": false,
        "Name": "AP-OpptyAddQLIforVBundle",
        "VlocityDataPackType": "SObject",
        "VlocityRecordSObjectType": "%vlocity_namespace%__DRMapItem__c"
    },
    {
        "%vlocity_namespace%__DomainObjectAPIName__c": "QuoteLineItem",
        "%vlocity_namespace%__DomainObjectCreationOrder__c": 1,
        "%vlocity_namespace%__DomainObjectFieldAPIName__c": "Competitor__c",
        "%vlocity_namespace%__FormulaOrder__c": 0,
        "%vlocity_namespace%__InterfaceFieldAPIName__c": "KeepCompId",
        "%vlocity_namespace%__InterfaceObjectName__c": "json",
        "%vlocity_namespace%__IsDisabled__c": false,
        "%vlocity_namespace%__IsRequiredForUpsert__c": false,
        "%vlocity_namespace%__LinkCreatedIndex__c": 0,
        "%vlocity_namespace%__MapId__c": "AP-OpptyAddQLIforVBundleCustom4427",
        "%vlocity_namespace%__UpsertKey__c": false,
        "Name": "AP-OpptyAddQLIforVBundle",
        "VlocityDataPackType": "SObject",
        "VlocityRecordSObjectType": "%vlocity_namespace%__DRMapItem__c"
    },
    {
        "%vlocity_namespace%__DomainObjectAPIName__c": "QuoteLineItem",
        "%vlocity_namespace%__DomainObjectCreationOrder__c": 1,
        "%vlocity_namespace%__DomainObjectFieldAPIName__c": "Financing__c",
        "%vlocity_namespace%__FormulaOrder__c": 0,
        "%vlocity_namespace%__InterfaceFieldAPIName__c": "QLD:QLD-Block:QLD-Financing",
        "%vlocity_namespace%__InterfaceObjectName__c": "json",
        "%vlocity_namespace%__IsDisabled__c": false,
        "%vlocity_namespace%__IsRequiredForUpsert__c": false,
        "%vlocity_namespace%__LinkCreatedIndex__c": 0,
        "%vlocity_namespace%__MapId__c": "AP-OpptyAddQLIforVBundleCustom9999",
        "%vlocity_namespace%__UpsertKey__c": false,
        "Name": "AP-OpptyAddQLIforVBundle",
        "VlocityDataPackType": "SObject",
        "VlocityRecordSObjectType": "%vlocity_namespace%__DRMapItem__c"
    },
    {
        "%vlocity_namespace%__DomainObjectAPIName__c": "QuoteLineItem",
        "%vlocity_namespace%__DomainObjectCreationOrder__c": 1,
        "%vlocity_namespace%__DomainObjectFieldAPIName__c": "Funding__c",
        "%vlocity_namespace%__FormulaOrder__c": 0,
        "%vlocity_namespace%__InterfaceFieldAPIName__c": "QLD:QLD-Block:QLD-Funding",
        "%vlocity_namespace%__InterfaceObjectName__c": "json",
        "%vlocity_namespace%__IsDisabled__c": false,
        "%vlocity_namespace%__IsRequiredForUpsert__c": false,
        "%vlocity_namespace%__LinkCreatedIndex__c": 0,
        "%vlocity_namespace%__MapId__c": "AP-OpptyAddQLIforVBundleCustom1449",
        "%vlocity_namespace%__UpsertKey__c": false,
        "Name": "AP-OpptyAddQLIforVBundle",
        "VlocityDataPackType": "SObject",
        "VlocityRecordSObjectType": "%vlocity_namespace%__DRMapItem__c"
    },
    {
        "%vlocity_namespace%__DomainObjectAPIName__c": "QuoteLineItem",
        "%vlocity_namespace%__DomainObjectCreationOrder__c": 1,
        "%vlocity_namespace%__DomainObjectFieldAPIName__c": "Members__c",
        "%vlocity_namespace%__FormulaOrder__c": 0,
        "%vlocity_namespace%__InterfaceFieldAPIName__c": "QuoteDetails:Members",
        "%vlocity_namespace%__InterfaceObjectName__c": "json",
        "%vlocity_namespace%__IsDisabled__c": false,
        "%vlocity_namespace%__IsRequiredForUpsert__c": false,
        "%vlocity_namespace%__LinkCreatedIndex__c": 0,
        "%vlocity_namespace%__MapId__c": "AP-OpptyAddQLIforVBundleCustom7217",
        "%vlocity_namespace%__UpsertKey__c": false,
        "Name": "AP-OpptyAddQLIforVBundle",
        "VlocityDataPackType": "SObject",
        "VlocityRecordSObjectType": "%vlocity_namespace%__DRMapItem__c"
    },
    {
        "%vlocity_namespace%__DomainObjectAPIName__c": "QuoteLineItem",
        "%vlocity_namespace%__DomainObjectCreationOrder__c": 1,
        "%vlocity_namespace%__DomainObjectFieldAPIName__c": "NOUFlag__c",
        "%vlocity_namespace%__FormulaOrder__c": 0,
        "%vlocity_namespace%__InterfaceFieldAPIName__c": "SelectServiceProvider:NOUFlag",
        "%vlocity_namespace%__InterfaceObjectName__c": "json",
        "%vlocity_namespace%__IsDisabled__c": false,
        "%vlocity_namespace%__IsRequiredForUpsert__c": false,
        "%vlocity_namespace%__LinkCreatedIndex__c": 0,
        "%vlocity_namespace%__MapId__c": "AP-OpptyAddQLIforVBundleCustom6458",
        "%vlocity_namespace%__UpsertKey__c": false,
        "Name": "AP-OpptyAddQLIforVBundle",
        "VlocityDataPackType": "SObject",
        "VlocityRecordSObjectType": "%vlocity_namespace%__DRMapItem__c"
    },
    {
        "%vlocity_namespace%__DomainObjectAPIName__c": "QuoteLineItem",
        "%vlocity_namespace%__DomainObjectCreationOrder__c": 1,
        "%vlocity_namespace%__DomainObjectFieldAPIName__c": "No_Sales_Credit__c",
        "%vlocity_namespace%__InterfaceFieldAPIName__c": "QLD:QLD-Block:QLD-NoSalesCredit",
        "%vlocity_namespace%__IsDisabled__c": false,
        "%vlocity_namespace%__IsRequiredForUpsert__c": false,
        "%vlocity_namespace%__MapId__c": "AP-OpptyAddQLIforVBundleCustom3072",
        "%vlocity_namespace%__UpsertKey__c": false,
        "Name": "AP-OpptyAddQLIforVBundle",
        "VlocityDataPackType": "SObject",
        "VlocityRecordSObjectType": "%vlocity_namespace%__DRMapItem__c"
    },
    {
        "%vlocity_namespace%__DomainObjectAPIName__c": "QuoteLineItem",
        "%vlocity_namespace%__DomainObjectCreationOrder__c": 1,
        "%vlocity_namespace%__DomainObjectFieldAPIName__c": "OppType__c",
        "%vlocity_namespace%__FormulaOrder__c": 0,
        "%vlocity_namespace%__InterfaceFieldAPIName__c": "QuoteDetails:OpptyRecType",
        "%vlocity_namespace%__InterfaceObjectName__c": "json",
        "%vlocity_namespace%__IsDisabled__c": false,
        "%vlocity_namespace%__IsRequiredForUpsert__c": false,
        "%vlocity_namespace%__LinkCreatedIndex__c": 0,
        "%vlocity_namespace%__MapId__c": "AP-OpptyAddQLIforVBundleCustom9961",
        "%vlocity_namespace%__UpsertKey__c": false,
        "Name": "AP-OpptyAddQLIforVBundle",
        "VlocityDataPackType": "SObject",
        "VlocityRecordSObjectType": "%vlocity_namespace%__DRMapItem__c"
    },
    {
        "%vlocity_namespace%__DomainObjectAPIName__c": "QuoteLineItem",
        "%vlocity_namespace%__DomainObjectCreationOrder__c": 1,
        "%vlocity_namespace%__DomainObjectFieldAPIName__c": "PricebookEntryId",
        "%vlocity_namespace%__FormulaOrder__c": 0,
        "%vlocity_namespace%__InterfaceFieldAPIName__c": "AP-ProductSelection:ProdList:Id",
        "%vlocity_namespace%__InterfaceObjectName__c": "json",
        "%vlocity_namespace%__IsDisabled__c": false,
        "%vlocity_namespace%__IsRequiredForUpsert__c": false,
        "%vlocity_namespace%__LinkCreatedIndex__c": 0,
        "%vlocity_namespace%__LookupDomainObjectFieldName__c": "Product2Id",
        "%vlocity_namespace%__LookupDomainObjectName__c": "PricebookEntry",
        "%vlocity_namespace%__LookupDomainObjectRequestedFieldName__c": "Id",
        "%vlocity_namespace%__MapId__c": "AP-OpptyAddQLIforVBundleCustom7144",
        "%vlocity_namespace%__UpsertKey__c": false,
        "Name": "AP-OpptyAddQLIforVBundle",
        "VlocityDataPackType": "SObject",
        "VlocityRecordSObjectType": "%vlocity_namespace%__DRMapItem__c"
    },
    {
        "%vlocity_namespace%__DefaultValue__c": "true",
        "%vlocity_namespace%__DomainObjectAPIName__c": "QuoteLineItem",
        "%vlocity_namespace%__DomainObjectCreationOrder__c": 1,
        "%vlocity_namespace%__DomainObjectFieldAPIName__c": "PricebookEntryId",
        "%vlocity_namespace%__FormulaOrder__c": 0,
        "%vlocity_namespace%__InterfaceObjectName__c": "json",
        "%vlocity_namespace%__IsDisabled__c": false,
        "%vlocity_namespace%__IsRequiredForUpsert__c": false,
        "%vlocity_namespace%__LinkCreatedIndex__c": 0,
        "%vlocity_namespace%__LookupDomainObjectFieldName__c": "IsActive",
        "%vlocity_namespace%__LookupDomainObjectName__c": "PricebookEntry",
        "%vlocity_namespace%__LookupDomainObjectRequestedFieldName__c": "Id",
        "%vlocity_namespace%__MapId__c": "AP-OpptyAddQLIforVBundleCustom1958",
        "%vlocity_namespace%__UpsertKey__c": false,
        "Name": "AP-OpptyAddQLIforVBundle",
        "VlocityDataPackType": "SObject",
        "VlocityRecordSObjectType": "%vlocity_namespace%__DRMapItem__c"
    },
    {
        "%vlocity_namespace%__DomainObjectAPIName__c": "QuoteLineItem",
        "%vlocity_namespace%__DomainObjectCreationOrder__c": 1,
        "%vlocity_namespace%__DomainObjectFieldAPIName__c": "Probability__c",
        "%vlocity_namespace%__FormulaOrder__c": 0,
        "%vlocity_namespace%__InterfaceFieldAPIName__c": "QLD:QLD-Block:QLD-Probability",
        "%vlocity_namespace%__InterfaceObjectName__c": "json",
        "%vlocity_namespace%__IsDisabled__c": false,
        "%vlocity_namespace%__IsRequiredForUpsert__c": false,
        "%vlocity_namespace%__LinkCreatedIndex__c": 0,
        "%vlocity_namespace%__MapId__c": "AP-OpptyAddQLIforVBundleCustom6590",
        "%vlocity_namespace%__UpsertKey__c": false,
        "Name": "AP-OpptyAddQLIforVBundle",
        "VlocityDataPackType": "SObject",
        "VlocityRecordSObjectType": "%vlocity_namespace%__DRMapItem__c"
    },
    {
        "%vlocity_namespace%__DomainObjectAPIName__c": "QuoteLineItem",
        "%vlocity_namespace%__DomainObjectCreationOrder__c": 1,
        "%vlocity_namespace%__DomainObjectFieldAPIName__c": "Product2Id",
        "%vlocity_namespace%__FormulaOrder__c": 0,
        "%vlocity_namespace%__InterfaceFieldAPIName__c": "AP-ProductSelection:ProdList:Id",
        "%vlocity_namespace%__InterfaceObjectName__c": "json",
        "%vlocity_namespace%__IsDisabled__c": false,
        "%vlocity_namespace%__IsRequiredForUpsert__c": false,
        "%vlocity_namespace%__LinkCreatedIndex__c": 0,
        "%vlocity_namespace%__MapId__c": "AP-OpptyAddQLIforVBundleCustom7361",
        "%vlocity_namespace%__UpsertKey__c": false,
        "Name": "AP-OpptyAddQLIforVBundle",
        "VlocityDataPackType": "SObject",
        "VlocityRecordSObjectType": "%vlocity_namespace%__DRMapItem__c"
    },
    {
        "%vlocity_namespace%__DomainObjectAPIName__c": "QuoteLineItem",
        "%vlocity_namespace%__DomainObjectCreationOrder__c": 1,
        "%vlocity_namespace%__DomainObjectFieldAPIName__c": "ProductStage__c",
        "%vlocity_namespace%__FormulaOrder__c": 0,
        "%vlocity_namespace%__InterfaceFieldAPIName__c": "QLD:QLD-Block:QLD-ProdStage",
        "%vlocity_namespace%__InterfaceObjectName__c": "json",
        "%vlocity_namespace%__IsDisabled__c": false,
        "%vlocity_namespace%__IsRequiredForUpsert__c": false,
        "%vlocity_namespace%__LinkCreatedIndex__c": 0,
        "%vlocity_namespace%__MapId__c": "AP-OpptyAddQLIforVBundleCustom5898",
        "%vlocity_namespace%__UpsertKey__c": false,
        "Name": "AP-OpptyAddQLIforVBundle",
        "VlocityDataPackType": "SObject",
        "VlocityRecordSObjectType": "%vlocity_namespace%__DRMapItem__c"
    },
    {
        "%vlocity_namespace%__DefaultValue__c": "1",
        "%vlocity_namespace%__DomainObjectAPIName__c": "QuoteLineItem",
        "%vlocity_namespace%__DomainObjectCreationOrder__c": 1,
        "%vlocity_namespace%__DomainObjectFieldAPIName__c": "Quantity",
        "%vlocity_namespace%__FormulaOrder__c": 0,
        "%vlocity_namespace%__InterfaceObjectName__c": "json",
        "%vlocity_namespace%__IsDisabled__c": false,
        "%vlocity_namespace%__IsRequiredForUpsert__c": false,
        "%vlocity_namespace%__LinkCreatedIndex__c": 0,
        "%vlocity_namespace%__MapId__c": "AP-OpptyAddQLIforVBundleCustom7162",
        "%vlocity_namespace%__UpsertKey__c": false,
        "Name": "AP-OpptyAddQLIforVBundle",
        "VlocityDataPackType": "SObject",
        "VlocityRecordSObjectType": "%vlocity_namespace%__DRMapItem__c"
    },
    {
        "%vlocity_namespace%__DomainObjectAPIName__c": "QuoteLineItem",
        "%vlocity_namespace%__DomainObjectCreationOrder__c": 1,
        "%vlocity_namespace%__DomainObjectFieldAPIName__c": "QuoteId",
        "%vlocity_namespace%__FormulaOrder__c": 0,
        "%vlocity_namespace%__InterfaceFieldAPIName__c": "QuoteDetails:Id",
        "%vlocity_namespace%__InterfaceObjectName__c": "json",
        "%vlocity_namespace%__IsDisabled__c": false,
        "%vlocity_namespace%__IsRequiredForUpsert__c": false,
        "%vlocity_namespace%__LinkCreatedIndex__c": 0,
        "%vlocity_namespace%__MapId__c": "AP-OpptyAddQLIforVBundleCustom4160",
        "%vlocity_namespace%__UpsertKey__c": false,
        "Name": "AP-OpptyAddQLIforVBundle",
        "VlocityDataPackType": "SObject",
        "VlocityRecordSObjectType": "%vlocity_namespace%__DRMapItem__c"
    },
    {
        "%vlocity_namespace%__DomainObjectAPIName__c": "QuoteLineItem",
        "%vlocity_namespace%__DomainObjectCreationOrder__c": 1,
        "%vlocity_namespace%__DomainObjectFieldAPIName__c": "Reason__c",
        "%vlocity_namespace%__FormulaOrder__c": 0,
        "%vlocity_namespace%__InterfaceFieldAPIName__c": "QLD:QLD-Block:QLD-Reason",
        "%vlocity_namespace%__InterfaceObjectName__c": "json",
        "%vlocity_namespace%__IsDisabled__c": false,
        "%vlocity_namespace%__IsRequiredForUpsert__c": false,
        "%vlocity_namespace%__LinkCreatedIndex__c": 0,
        "%vlocity_namespace%__MapId__c": "AP-OpptyAddQLIforVBundleCustom8329",
        "%vlocity_namespace%__UpsertKey__c": false,
        "Name": "AP-OpptyAddQLIforVBundle",
        "VlocityDataPackType": "SObject",
        "VlocityRecordSObjectType": "%vlocity_namespace%__DRMapItem__c"
    },
    {
        "%vlocity_namespace%__DomainObjectAPIName__c": "QuoteLineItem",
        "%vlocity_namespace%__DomainObjectCreationOrder__c": 1,
        "%vlocity_namespace%__DomainObjectFieldAPIName__c": "RecordType__c",
        "%vlocity_namespace%__FormulaOrder__c": 0,
        "%vlocity_namespace%__InterfaceFieldAPIName__c": "AP-ProductSelection:ProdList:QLIRecordType__c",
        "%vlocity_namespace%__InterfaceObjectName__c": "json",
        "%vlocity_namespace%__IsDisabled__c": false,
        "%vlocity_namespace%__IsRequiredForUpsert__c": false,
        "%vlocity_namespace%__LinkCreatedIndex__c": 0,
        "%vlocity_namespace%__MapId__c": "AP-OpptyAddQLIforVBundleCustom4553",
        "%vlocity_namespace%__UpsertKey__c": false,
        "Name": "AP-OpptyAddQLIforVBundle",
        "VlocityDataPackType": "SObject",
        "VlocityRecordSObjectType": "%vlocity_namespace%__DRMapItem__c"
    },
    {
        "%vlocity_namespace%__DomainObjectAPIName__c": "QuoteLineItem",
        "%vlocity_namespace%__DomainObjectCreationOrder__c": 1,
        "%vlocity_namespace%__DomainObjectFieldAPIName__c": "Subscribers__c",
        "%vlocity_namespace%__FormulaOrder__c": 0,
        "%vlocity_namespace%__InterfaceFieldAPIName__c": "QuoteDetails:Subscribers",
        "%vlocity_namespace%__InterfaceObjectName__c": "json",
        "%vlocity_namespace%__IsDisabled__c": false,
        "%vlocity_namespace%__IsRequiredForUpsert__c": false,
        "%vlocity_namespace%__LinkCreatedIndex__c": 0,
        "%vlocity_namespace%__MapId__c": "AP-OpptyAddQLIforVBundleCustom3295",
        "%vlocity_namespace%__UpsertKey__c": false,
        "Name": "AP-OpptyAddQLIforVBundle",
        "VlocityDataPackType": "SObject",
        "VlocityRecordSObjectType": "%vlocity_namespace%__DRMapItem__c"
    },
    {
        "%vlocity_namespace%__DomainObjectAPIName__c": "QuoteLineItem",
        "%vlocity_namespace%__DomainObjectCreationOrder__c": 1,
        "%vlocity_namespace%__DomainObjectFieldAPIName__c": "TECH_OSIsMultiSelect__c",
        "%vlocity_namespace%__FormulaOrder__c": 0,
        "%vlocity_namespace%__InterfaceFieldAPIName__c": "AP-Selected",
        "%vlocity_namespace%__InterfaceObjectName__c": "json",
        "%vlocity_namespace%__IsDisabled__c": false,
        "%vlocity_namespace%__IsRequiredForUpsert__c": false,
        "%vlocity_namespace%__LinkCreatedIndex__c": 0,
        "%vlocity_namespace%__MapId__c": "AP-OpptyAddQLIforVBundleCustom301",
        "%vlocity_namespace%__UpsertKey__c": false,
        "Name": "AP-OpptyAddQLIforVBundle",
        "VlocityDataPackType": "SObject",
        "VlocityRecordSObjectType": "%vlocity_namespace%__DRMapItem__c"
    },
    {
        "%vlocity_namespace%__DomainObjectAPIName__c": "QuoteLineItem",
        "%vlocity_namespace%__DomainObjectCreationOrder__c": 1,
        "%vlocity_namespace%__DomainObjectFieldAPIName__c": "TermDate__c",
        "%vlocity_namespace%__FormulaOrder__c": 0,
        "%vlocity_namespace%__InterfaceFieldAPIName__c": "QLD:QLD-Block:QLD-TermDate",
        "%vlocity_namespace%__InterfaceObjectName__c": "json",
        "%vlocity_namespace%__IsDisabled__c": false,
        "%vlocity_namespace%__IsRequiredForUpsert__c": false,
        "%vlocity_namespace%__LinkCreatedIndex__c": 0,
        "%vlocity_namespace%__MapId__c": "AP-OpptyAddQLIforVBundleCustom78",
        "%vlocity_namespace%__UpsertKey__c": false,
        "Name": "AP-OpptyAddQLIforVBundle",
        "VlocityDataPackType": "SObject",
        "VlocityRecordSObjectType": "%vlocity_namespace%__DRMapItem__c"
    },
    {
        "%vlocity_namespace%__DefaultValue__c": "0",
        "%vlocity_namespace%__DomainObjectAPIName__c": "QuoteLineItem",
        "%vlocity_namespace%__DomainObjectCreationOrder__c": 1,
        "%vlocity_namespace%__DomainObjectFieldAPIName__c": "UnitPrice",
        "%vlocity_namespace%__FormulaOrder__c": 0,
        "%vlocity_namespace%__InterfaceObjectName__c": "json",
        "%vlocity_namespace%__IsDisabled__c": false,
        "%vlocity_namespace%__IsRequiredForUpsert__c": false,
        "%vlocity_namespace%__LinkCreatedIndex__c": 0,
        "%vlocity_namespace%__MapId__c": "AP-OpptyAddQLIforVBundleCustom8388",
        "%vlocity_namespace%__UpsertKey__c": false,
        "Name": "AP-OpptyAddQLIforVBundle",
        "VlocityDataPackType": "SObject",
        "VlocityRecordSObjectType": "%vlocity_namespace%__DRMapItem__c"
    },
    {
        "%vlocity_namespace%__DomainObjectAPIName__c": "QuoteLineItem",
        "%vlocity_namespace%__DomainObjectCreationOrder__c": 2,
        "%vlocity_namespace%__DomainObjectFieldAPIName__c": "OppType__c",
        "%vlocity_namespace%__FormulaOrder__c": 0,
        "%vlocity_namespace%__InterfaceFieldAPIName__c": "QuoteDetails:OpptyRecType",
        "%vlocity_namespace%__InterfaceObjectName__c": "json",
        "%vlocity_namespace%__IsDisabled__c": false,
        "%vlocity_namespace%__IsRequiredForUpsert__c": false,
        "%vlocity_namespace%__LinkCreatedIndex__c": 0,
        "%vlocity_namespace%__MapId__c": "AP-OpptyAddQLIforVBundleCustom1768",
        "%vlocity_namespace%__UpsertKey__c": false,
        "Name": "AP-OpptyAddQLIforVBundle",
        "VlocityDataPackType": "SObject",
        "VlocityRecordSObjectType": "%vlocity_namespace%__DRMapItem__c"
    },
    {
        "%vlocity_namespace%__DomainObjectAPIName__c": "QuoteLineItem",
        "%vlocity_namespace%__DomainObjectCreationOrder__c": 2,
        "%vlocity_namespace%__DomainObjectFieldAPIName__c": "ParentQuoteLineItem__c",
        "%vlocity_namespace%__FormulaOrder__c": 0,
        "%vlocity_namespace%__InterfaceObjectName__c": "json",
        "%vlocity_namespace%__IsDisabled__c": false,
        "%vlocity_namespace%__IsRequiredForUpsert__c": false,
        "%vlocity_namespace%__LinkCreatedField__c": "Id",
        "%vlocity_namespace%__LinkCreatedIndex__c": 1,
        "%vlocity_namespace%__MapId__c": "AP-OpptyAddQLIforVBundleCustom8331",
        "%vlocity_namespace%__UpsertKey__c": false,
        "Name": "AP-OpptyAddQLIforVBundle",
        "VlocityDataPackType": "SObject",
        "VlocityRecordSObjectType": "%vlocity_namespace%__DRMapItem__c"
    },
    {
        "%vlocity_namespace%__DomainObjectAPIName__c": "QuoteLineItem",
        "%vlocity_namespace%__DomainObjectCreationOrder__c": 2,
        "%vlocity_namespace%__DomainObjectFieldAPIName__c": "PricebookEntryId",
        "%vlocity_namespace%__FormulaOrder__c": 0,
        "%vlocity_namespace%__InterfaceFieldAPIName__c": "AP-BundleSelection:BundleList:Id",
        "%vlocity_namespace%__InterfaceObjectName__c": "json",
        "%vlocity_namespace%__IsDisabled__c": false,
        "%vlocity_namespace%__IsRequiredForUpsert__c": false,
        "%vlocity_namespace%__LinkCreatedIndex__c": 0,
        "%vlocity_namespace%__LookupDomainObjectFieldName__c": "Product2Id",
        "%vlocity_namespace%__LookupDomainObjectName__c": "PricebookEntry",
        "%vlocity_namespace%__LookupDomainObjectRequestedFieldName__c": "Id",
        "%vlocity_namespace%__MapId__c": "AP-OpptyAddQLIforVBundleCustom7854",
        "%vlocity_namespace%__UpsertKey__c": false,
        "Name": "AP-OpptyAddQLIforVBundle",
        "VlocityDataPackType": "SObject",
        "VlocityRecordSObjectType": "%vlocity_namespace%__DRMapItem__c"
    },
    {
        "%vlocity_namespace%__DefaultValue__c": "true",
        "%vlocity_namespace%__DomainObjectAPIName__c": "QuoteLineItem",
        "%vlocity_namespace%__DomainObjectCreationOrder__c": 2,
        "%vlocity_namespace%__DomainObjectFieldAPIName__c": "PricebookEntryId",
        "%vlocity_namespace%__FormulaOrder__c": 0,
        "%vlocity_namespace%__InterfaceObjectName__c": "json",
        "%vlocity_namespace%__IsDisabled__c": false,
        "%vlocity_namespace%__IsRequiredForUpsert__c": false,
        "%vlocity_namespace%__LinkCreatedIndex__c": 0,
        "%vlocity_namespace%__LookupDomainObjectFieldName__c": "IsActive",
        "%vlocity_namespace%__LookupDomainObjectName__c": "PricebookEntry",
        "%vlocity_namespace%__LookupDomainObjectRequestedFieldName__c": "Id",
        "%vlocity_namespace%__MapId__c": "AP-OpptyAddQLIforVBundleCustom4042",
        "%vlocity_namespace%__UpsertKey__c": false,
        "Name": "AP-OpptyAddQLIforVBundle",
        "VlocityDataPackType": "SObject",
        "VlocityRecordSObjectType": "%vlocity_namespace%__DRMapItem__c"
    },
    {
        "%vlocity_namespace%__DomainObjectAPIName__c": "QuoteLineItem",
        "%vlocity_namespace%__DomainObjectCreationOrder__c": 2,
        "%vlocity_namespace%__DomainObjectFieldAPIName__c": "Product2Id",
        "%vlocity_namespace%__FormulaOrder__c": 0,
        "%vlocity_namespace%__InterfaceFieldAPIName__c": "AP-BundleSelection:BundleList:Id",
        "%vlocity_namespace%__InterfaceObjectName__c": "json",
        "%vlocity_namespace%__IsDisabled__c": false,
        "%vlocity_namespace%__IsRequiredForUpsert__c": false,
        "%vlocity_namespace%__LinkCreatedIndex__c": 0,
        "%vlocity_namespace%__MapId__c": "AP-OpptyAddQLIforVBundleCustom9947",
        "%vlocity_namespace%__UpsertKey__c": false,
        "Name": "AP-OpptyAddQLIforVBundle",
        "VlocityDataPackType": "SObject",
        "VlocityRecordSObjectType": "%vlocity_namespace%__DRMapItem__c"
    },
    {
        "%vlocity_namespace%__DomainObjectAPIName__c": "QuoteLineItem",
        "%vlocity_namespace%__DomainObjectCreationOrder__c": 2,
        "%vlocity_namespace%__DomainObjectFieldAPIName__c": "ProductStage__c",
        "%vlocity_namespace%__FormulaOrder__c": 0,
        "%vlocity_namespace%__InterfaceFieldAPIName__c": "AP-BundleSelection:BundleList:vlcBundleStage",
        "%vlocity_namespace%__InterfaceObjectName__c": "json",
        "%vlocity_namespace%__IsDisabled__c": false,
        "%vlocity_namespace%__IsRequiredForUpsert__c": false,
        "%vlocity_namespace%__LinkCreatedIndex__c": 0,
        "%vlocity_namespace%__MapId__c": "AP-OpptyAddQLIforVBundleCustom1802",
        "%vlocity_namespace%__UpsertKey__c": false,
        "Name": "AP-OpptyAddQLIforVBundle",
        "VlocityDataPackType": "SObject",
        "VlocityRecordSObjectType": "%vlocity_namespace%__DRMapItem__c"
    },
    {
        "%vlocity_namespace%__DefaultValue__c": "1",
        "%vlocity_namespace%__DomainObjectAPIName__c": "QuoteLineItem",
        "%vlocity_namespace%__DomainObjectCreationOrder__c": 2,
        "%vlocity_namespace%__DomainObjectFieldAPIName__c": "Quantity",
        "%vlocity_namespace%__FormulaOrder__c": 0,
        "%vlocity_namespace%__InterfaceObjectName__c": "json",
        "%vlocity_namespace%__IsDisabled__c": false,
        "%vlocity_namespace%__IsRequiredForUpsert__c": false,
        "%vlocity_namespace%__LinkCreatedIndex__c": 0,
        "%vlocity_namespace%__MapId__c": "AP-OpptyAddQLIforVBundleCustom7215",
        "%vlocity_namespace%__UpsertKey__c": false,
        "Name": "AP-OpptyAddQLIforVBundle",
        "VlocityDataPackType": "SObject",
        "VlocityRecordSObjectType": "%vlocity_namespace%__DRMapItem__c"
    },
    {
        "%vlocity_namespace%__DomainObjectAPIName__c": "QuoteLineItem",
        "%vlocity_namespace%__DomainObjectCreationOrder__c": 2,
        "%vlocity_namespace%__DomainObjectFieldAPIName__c": "QuoteId",
        "%vlocity_namespace%__FormulaOrder__c": 0,
        "%vlocity_namespace%__InterfaceFieldAPIName__c": "QuoteDetails:Id",
        "%vlocity_namespace%__InterfaceObjectName__c": "json",
        "%vlocity_namespace%__IsDisabled__c": false,
        "%vlocity_namespace%__IsRequiredForUpsert__c": false,
        "%vlocity_namespace%__LinkCreatedIndex__c": 0,
        "%vlocity_namespace%__MapId__c": "AP-OpptyAddQLIforVBundleCustom2684",
        "%vlocity_namespace%__UpsertKey__c": false,
        "Name": "AP-OpptyAddQLIforVBundle",
        "VlocityDataPackType": "SObject",
        "VlocityRecordSObjectType": "%vlocity_namespace%__DRMapItem__c"
    },
    {
        "%vlocity_namespace%__DomainObjectAPIName__c": "QuoteLineItem",
        "%vlocity_namespace%__DomainObjectCreationOrder__c": 2,
        "%vlocity_namespace%__DomainObjectFieldAPIName__c": "RecordType__c",
        "%vlocity_namespace%__FormulaOrder__c": 0,
        "%vlocity_namespace%__InterfaceFieldAPIName__c": "AP-BundleSelection:BundleList:QLIRecordType__c",
        "%vlocity_namespace%__InterfaceObjectName__c": "json",
        "%vlocity_namespace%__IsDisabled__c": false,
        "%vlocity_namespace%__IsRequiredForUpsert__c": false,
        "%vlocity_namespace%__LinkCreatedIndex__c": 0,
        "%vlocity_namespace%__MapId__c": "AP-OpptyAddQLIforVBundleCustom6482",
        "%vlocity_namespace%__UpsertKey__c": false,
        "Name": "AP-OpptyAddQLIforVBundle",
        "VlocityDataPackType": "SObject",
        "VlocityRecordSObjectType": "%vlocity_namespace%__DRMapItem__c"
    },
    {
        "%vlocity_namespace%__DefaultValue__c": "1",
        "%vlocity_namespace%__DomainObjectAPIName__c": "QuoteLineItem",
        "%vlocity_namespace%__DomainObjectCreationOrder__c": 2,
        "%vlocity_namespace%__DomainObjectFieldAPIName__c": "UnitPrice",
        "%vlocity_namespace%__FormulaOrder__c": 0,
        "%vlocity_namespace%__InterfaceObjectName__c": "json",
        "%vlocity_namespace%__IsDisabled__c": false,
        "%vlocity_namespace%__IsRequiredForUpsert__c": false,
        "%vlocity_namespace%__LinkCreatedIndex__c": 0,
        "%vlocity_namespace%__MapId__c": "AP-OpptyAddQLIforVBundleCustom3035",
        "%vlocity_namespace%__UpsertKey__c": false,
        "Name": "AP-OpptyAddQLIforVBundle",
        "VlocityDataPackType": "SObject",
        "VlocityRecordSObjectType": "%vlocity_namespace%__DRMapItem__c"
    }
]